Cargo.lock
Cargo.toml
zakat-core/Cargo.toml
zakat-core/LICENSE
zakat-core/README.md
zakat-core/pyproject.toml
zakat-core/src/assets.rs
zakat-core/src/config.rs
zakat-core/src/debt.rs
zakat-core/src/distribution.rs
zakat-core/src/fitrah.rs
zakat-core/src/hawl.rs
zakat-core/src/inputs.rs
zakat-core/src/kotlin.rs
zakat-core/src/lib.rs
zakat-core/src/maal/agriculture.rs
zakat-core/src/maal/business.rs
zakat-core/src/maal/calculator.rs
zakat-core/src/maal/income.rs
zakat-core/src/maal/investments.rs
zakat-core/src/maal/livestock.rs
zakat-core/src/maal/mining.rs
zakat-core/src/maal/mod.rs
zakat-core/src/maal/precious_metals.rs
zakat-core/src/maal/restricted.rs
zakat-core/src/macros.rs
zakat-core/src/madhab.rs
zakat-core/src/math.rs
zakat-core/src/partnership.rs
zakat-core/src/portfolio.rs
zakat-core/src/prelude.rs
zakat-core/src/python.rs
zakat-core/src/traits.rs
zakat-core/src/types.rs
zakat-core/src/utils.rs
zakat-core/src/validation.rs
zakat-core/tests/api_ergonomics.rs
zakat-core/tests/fiqh_advanced.rs
zakat-core/tests/gen_py_stubs.rs
zakat-core/zakatrs.pyi
zakat-i18n/Cargo.toml
zakat-i18n/LICENSE
zakat-i18n/README.md
zakat-i18n/assets/locales/ar-SA/main.ftl
zakat-i18n/assets/locales/en-US/main.ftl
zakat-i18n/assets/locales/id-ID/main.ftl
zakat-i18n/src/i18n.rs
zakat-i18n/src/lib.rs
zakat-ledger/Cargo.toml
zakat-ledger/LICENSE
zakat-ledger/README.md
zakat-ledger/src/analyzer.rs
zakat-ledger/src/assets.rs
zakat-ledger/src/events.rs
zakat-ledger/src/hawl.rs
zakat-ledger/src/lib.rs
zakat-ledger/src/pricing.rs
zakat-ledger/src/qada.rs
zakat-ledger/src/qada_inflation.rs
zakat-ledger/src/timeline.rs
zakat-providers/Cargo.toml
zakat-providers/LICENSE
zakat-providers/README.md
zakat-providers/src/chain.rs
zakat-providers/src/fs_cache.rs
zakat-providers/src/lib.rs
zakat-providers/src/pricing.rs
zakat-sqlite/Cargo.toml
zakat-sqlite/LICENSE
zakat-sqlite/README.md
zakat-sqlite/src/lib.rs
zakat-sqlite/src/persistence.rs
zakat-sqlite/src/sqlite.rs
zakat/Cargo.toml
zakat/LICENSE
zakatrs-1.4.0.dist-info/METADATA
zakatrs-1.4.0.dist-info/WHEEL
zakatrs-1.4.0.dist-info/licenses/LICENSE
zakatrs-1.4.0.dist-info/RECORD
