Metadata-Version: 2.4
Name: zakatrs
Version: 1.4.0
Classifier: Programming Language :: Rust
Classifier: Programming Language :: Python :: Implementation :: CPython
Classifier: Programming Language :: Python :: Implementation :: PyPy
Classifier: Development Status :: 5 - Production/Stable
Classifier: Intended Audience :: Developers
Classifier: License :: OSI Approved :: MIT License
Classifier: Topic :: Office/Business :: Financial :: Accounting
Classifier: Topic :: Religion
License-File: LICENSE
Summary: A type-safe, comprehensive, and Fiqh-compliant Zakat calculation library with high-precision decimal support.
Keywords: zakat,islamic-finance,fiqh,halal,rust,decimal-precision
Author-email: "Mohammad Farid Hendianto (IRedDragonICY)" <mfrfrdhndnt@gmail.com>
Requires-Python: >=3.8
Project-URL: Homepage, https://github.com/IRedDragonICY/zakatrs
Project-URL: Repository, https://github.com/IRedDragonICY/zakatrs
Project-URL: Documentation, https://github.com/IRedDragonICY/zakatrs#readme
